xapres_package/ApRESDefs.py
xapres_package/ApRES_plot.py
xapres_package/__init__.py
xapres_package/_version.py
xapres_package/dummy_module.py
xapres_package-0.1.0.dist-info/LICENSE.txt
xapres_package-0.1.0.dist-info/METADATA
xapres_package-0.1.0.dist-info/WHEEL
xapres_package-0.1.0.dist-info/top_level.txt
xapres_package-0.1.0.dist-info/RECORD
