Metadata-Version: 2.1
Name: xapres-package
Version: 0.1.0
Summary: Code for processing ApRES data suing xarray
Home-page: https://github.com/jkingslake/xapres_package
Author: ldeo_glaciology
Author-email: j.kingslake@columbia.edu
License: MIT
Classifier: Development Status :: 2 - Pre-Alpha
Classifier: Topic :: Scientific/Engineering
Classifier: Intended Audience :: Science/Research
Classifier: Operating System :: OS Independent
Classifier: Programming Language :: Python
Classifier: Programming Language :: Python :: 3
Classifier: Programming Language :: Python :: 3.6
Classifier: Programming Language :: Python :: 3.7
Classifier: Programming Language :: Python :: 3.8
Classifier: License :: OSI Approved :: MIT License
Requires-Python: >=3.6
License-File: LICENSE.txt
Requires-Dist: numpy
Requires-Dist: requests
Requires-Dist: xarray
Requires-Dist: gcsfs
Requires-Dist: fsspec
Requires-Dist: pandas
Requires-Dist: tqdm
